hubble_shuttle/__init__.py
hubble_shuttle/api.py
hubble_shuttle/exceptions.py
hubble_shuttle/http.py
hubble_shuttle-0.6.2.dist-info/METADATA
hubble_shuttle-0.6.2.dist-info/WHEEL
hubble_shuttle-0.6.2.dist-info/licenses/LICENSE
hubble_shuttle-0.6.2.dist-info/RECORD
