Metadata-Version: 2.4
Name: hubble_shuttle
Version: 0.6.2
Summary: Hubble's Shuttle
Project-URL: Homepage, https://github.com/HubbleHQ/shuttle
Project-URL: Repository, https://github.com/HubbleHQ/shuttle.git
Author-email: Hubble <dev@hubblehq.com>
License-File: LICENSE
Classifier: Development Status :: 3 - Alpha
Classifier: License :: OSI Approved :: MIT License
Classifier: Operating System :: OS Independent
Classifier: Programming Language :: Python :: 3
Requires-Python: >=3.9
Requires-Dist: requests>2.32.0
